dataharvest/__init__.py
dataharvest/base.py
dataharvest/schema.py
dataharvest/proxy/__init__.py
dataharvest/proxy/base.py
dataharvest/purifier/__init__.py
dataharvest/purifier/baidu_purifier.py
dataharvest/purifier/base.py
dataharvest/purifier/bilibili_purifier.py
dataharvest/purifier/common_purifier.py
dataharvest/purifier/purifier.py
dataharvest/purifier/qqnew_purifier.py
dataharvest/purifier/sll_purifier.py
dataharvest/purifier/sobaike_purifier.py
dataharvest/purifier/sogou_purifier.py
dataharvest/purifier/sohu_purifier.py
dataharvest/purifier/toutiao_purifier.py
dataharvest/purifier/wangyi_purifier.py
dataharvest/purifier/wechat_purifier.py
dataharvest/purifier/xiaohongshu_purifier.py
dataharvest/searcher/__init__.py
dataharvest/searcher/base.py
dataharvest/searcher/sky_searcher.py
dataharvest/searcher/tavily_searcher.py
dataharvest/spider/__init__.py
dataharvest/spider/base.py
dataharvest/spider/common_spider.py
dataharvest/spider/spider.py
dataharvest/spider/ssl_spider.py
dataharvest/spider/toutiao_spider.py
dataharvest/spider/utils.py
dataharvest/spider/xiaohongshu_spider.py
dataharvest-0.2.14.dist-info/METADATA
dataharvest-0.2.14.dist-info/WHEEL
dataharvest-0.2.14.dist-info/RECORD
