Metadata-Version: 2.3
Name: dataharvest
Version: 0.2.14
Summary: Add your description here
Author-email: yuvenhol <yuvenhol@gmail.com>
Requires-Python: >=3.8
Requires-Dist: cssutils>=2.11.1
Requires-Dist: html2text>=2024.2.26
Requires-Dist: httpx>=0.27.0
Requires-Dist: parsel>=1.9.1
Requires-Dist: playwright-stealth>=1.0.6
Requires-Dist: playwright>=1.44.0
